{
    "refreshTimeStamp": 1764109216,
    "refreshTimeCH": "2025-11-26 06:20:16",
    "timezone": "utc+8",
    "OJType": [
        "codeforces",
        "atcoder",
        "luogu",
        "nowcoder",
        "leetcode"
    ],
    "contests": [
        {
            "oj": "luogu",
            "name": "NOIP 模板自测赛",
            "stime": 1764039600,
            "etime": 1764376200,
            "dtime": 336600,
            "link": "https://www.luogu.com.cn/contest/293606"
        },
        {
            "oj": "nowcoder",
            "name": "牛客小白月赛124",
            "stime": 1764327600,
            "etime": 1764334800,
            "dtime": 7200,
            "link": "https://ac.nowcoder.com/acm/contest/123787"
        },
        {
            "oj": "codeforces",
            "name": "Educational Codeforces Round 185 (Rated for Div. 2)",
            "stime": 1764340500,
            "etime": 1764347700,
            "dtime": 7200,
            "link": "https://codeforces.com/contest/2170"
        },
        {
            "oj": "atcoder",
            "name": "AtCoder Heuristic Contest 057",
            "stime": 1764396000,
            "etime": 1764410400,
            "dtime": 14400,
            "link": "https://atcoder.jp/contests/ahc057"
        },
        {
            "oj": "atcoder",
            "name": "Ｓｋｙ Inc, Programming Contest 2025 (AtCoder Beginner Contest 434)",
            "stime": 1764417600,
            "etime": 1764423600,
            "dtime": 6000,
            "link": "https://atcoder.jp/contests/abc434"
        },
        {
            "oj": "leetcode",
            "name": "Weekly Contest 478",
            "stime": 1764469800,
            "etime": 1764475200,
            "dtime": 5400,
            "link": "https://leetcode.cn/contest/weekly-contest-478"
        },
        {
            "oj": "luogu",
            "name": "OIMO Round 1",
            "stime": 1764480600,
            "etime": 1764491400,
            "dtime": 10800,
            "link": "https://www.luogu.com.cn/contest/251007"
        },
        {
            "oj": "nowcoder",
            "name": "牛客周赛 Round 120",
            "stime": 1764500400,
            "etime": 1764507600,
            "dtime": 7200,
            "link": "https://ac.nowcoder.com/acm/contest/123788"
        },
        {
            "oj": "atcoder",
            "name": "AtCoder Regular Contest 211 (Div. 2)",
            "stime": 1764504000,
            "etime": 1764511200,
            "dtime": 7200,
            "link": "https://atcoder.jp/contests/arc211"
        },
        {
            "oj": "nowcoder",
            "name": "牛客挑战赛84",
            "stime": 1764932400,
            "etime": 1764943200,
            "dtime": 10800,
            "link": "https://ac.nowcoder.com/acm/contest/124146"
        },
        {
            "oj": "atcoder",
            "name": "AtCoder Beginner Contest 435",
            "stime": 1765022400,
            "etime": 1765028400,
            "dtime": 6000,
            "link": "https://atcoder.jp/contests/abc435"
        },
        {
            "oj": "leetcode",
            "name": "Biweekly Contest 171",
            "stime": 1765031400,
            "etime": 1765036800,
            "dtime": 5400,
            "link": "https://leetcode.cn/contest/biweekly-contest-171"
        },
        {
            "oj": "leetcode",
            "name": "Weekly Contest 479",
            "stime": 1765074600,
            "etime": 1765080000,
            "dtime": 5400,
            "link": "https://leetcode.cn/contest/weekly-contest-479"
        },
        {
            "oj": "luogu",
            "name": "【LGR-253-Div.3】洛谷基础赛 #28 & KenOI Round 1",
            "stime": 1765087200,
            "etime": 1765099800,
            "dtime": 12600,
            "link": "https://www.luogu.com.cn/contest/254710"
        },
        {
            "oj": "nowcoder",
            "name": "牛客周赛 Round 121",
            "stime": 1765105200,
            "etime": 1765112400,
            "dtime": 7200,
            "link": "https://ac.nowcoder.com/acm/contest/124143"
        },
        {
            "oj": "atcoder",
            "name": "AtCoder Beginner Contest 436",
            "stime": 1765627200,
            "etime": 1765633200,
            "dtime": 6000,
            "link": "https://atcoder.jp/contests/abc436"
        },
        {
            "oj": "atcoder",
            "name": "ALGO ARTIS Programming Contest 2025 December（AtCoder Heuristic Contest 058）",
            "stime": 1765692000,
            "etime": 1765706400,
            "dtime": 14400,
            "link": "https://atcoder.jp/contests/ahc058"
        },
        {
            "oj": "atcoder",
            "name": "UNIQUE VISION Programming Contest 2025 Christmas (AtCoder Beginner Contest 437)",
            "stime": 1766232000,
            "etime": 1766238000,
            "dtime": 6000,
            "link": "https://atcoder.jp/contests/abc437"
        },
        {
            "oj": "atcoder",
            "name": "AtCoder Grand Contest 075",
            "stime": 1766318400,
            "etime": 1766329200,
            "dtime": 10800,
            "link": "https://atcoder.jp/contests/agc075"
        },
        {
            "oj": "atcoder",
            "name": "AtCoder Beginner Contest 438",
            "stime": 1766836800,
            "etime": 1766842800,
            "dtime": 6000,
            "link": "https://atcoder.jp/contests/abc438"
        },
        {
            "oj": "atcoder",
            "name": "AtCoder Grand Contest 076",
            "stime": 1766923200,
            "etime": 1766934000,
            "dtime": 10800,
            "link": "https://atcoder.jp/contests/agc076"
        },
        {
            "oj": "nowcoder",
            "name": "2026牛客寒假算法基础集训营1",
            "stime": 1770098400,
            "etime": 1770112800,
            "dtime": 14400,
            "link": "https://ac.nowcoder.com/acm/contest/120561"
        }
    ]
}